html_editor/__init__.py
html_editor/html_editor.py
html_editor-1.0.dist-info/METADATA
html_editor-1.0.dist-info/WHEEL
html_editor-1.0.dist-info/top_level.txt
html_editor-1.0.dist-info/RECORD
