Metadata-Version: 2.1
Name: html-editor
Version: 1.0
Summary: A library to create HTML pages.
Home-page: UNKNOWN
Author: LesCodeursProsLFJM
License: MIT
Platform: UNKNOWN
